livermask/__init__.py
livermask/livermask.py
livermask/configs/__init__.py
livermask/configs/base.yml
livermask/utils/__init__.py
livermask/utils/fetch.py
livermask/utils/process.py
livermask/utils/unet3d.py
livermask/utils/utils.py
livermask/utils/yaml_utils.py
livermask-1.4.1.dist-info/LICENSE.md
livermask-1.4.1.dist-info/METADATA
livermask-1.4.1.dist-info/WHEEL
livermask-1.4.1.dist-info/entry_points.txt
livermask-1.4.1.dist-info/top_level.txt
livermask-1.4.1.dist-info/RECORD
