Metadata-Version: 2.1
Name: livermask
Version: 1.4.1
Summary: A package for automatic segmentation of liver from CT data
Home-page: https://github.com/andreped/livermask
Author: André Pedersen and Javier Pérez de Frutos
Author-email: andrped94@gmail.com
License: MIT
Classifier: Programming Language :: Python :: 3.6
Classifier: Programming Language :: Python :: 3.7
Classifier: Programming Language :: Python :: 3.8
Classifier: License :: OSI Approved :: MIT License
Classifier: Operating System :: OS Independent
Requires-Python: >=3.6
License-File: LICENSE.md
Requires-Dist: absl-py (==0.13.0)
Requires-Dist: astunparse (==1.6.3)
Requires-Dist: cached-property (==1.5.2)
Requires-Dist: cachetools (==4.2.2)
Requires-Dist: certifi (==2021.5.30)
Requires-Dist: chainer (==7.8.0)
Requires-Dist: charset-normalizer (==2.0.4)
Requires-Dist: clang (==5.0)
Requires-Dist: colorama (==0.4.4)
Requires-Dist: cycler (==0.10.0)
Requires-Dist: decorator (==4.4.2)
Requires-Dist: fastrlock (==0.8)
Requires-Dist: filelock (==3.0.12)
Requires-Dist: flatbuffers (==1.12)
Requires-Dist: gast (==0.3.3)
Requires-Dist: gdown (==4.5.3)
Requires-Dist: google-auth (==1.35.0)
Requires-Dist: google-auth-oauthlib (==0.4.6)
Requires-Dist: google-pasta (==0.2.0)
Requires-Dist: grpcio (==1.32.0)
Requires-Dist: h5py (==2.10.0)
Requires-Dist: idna (==3.2)
Requires-Dist: imageio (==2.9.0)
Requires-Dist: importlib-metadata (==4.8.1)
Requires-Dist: keras (==2.6.0)
Requires-Dist: Keras-Preprocessing (==1.1.2)
Requires-Dist: kiwisolver (==1.3.1)
Requires-Dist: llvmlite (==0.36.0)
Requires-Dist: Markdown (==3.3.4)
Requires-Dist: matplotlib (==3.3.4)
Requires-Dist: networkx (==2.5.1)
Requires-Dist: nibabel (==3.2.1)
Requires-Dist: numba (==0.53.1)
Requires-Dist: numpy (==1.19.5)
Requires-Dist: oauthlib (==3.1.1)
Requires-Dist: opt-einsum (==3.3.0)
Requires-Dist: packaging (==21.0)
Requires-Dist: Pillow (==8.3.2)
Requires-Dist: protobuf (==3.17.3)
Requires-Dist: pyasn1 (==0.4.8)
Requires-Dist: pyasn1-modules (==0.2.8)
Requires-Dist: pyparsing (==2.4.7)
Requires-Dist: PySocks (==1.7.1)
Requires-Dist: python-dateutil (==2.8.2)
Requires-Dist: PyWavelets (==1.1.1)
Requires-Dist: PyYAML (==6.0)
Requires-Dist: requests (==2.26.0)
Requires-Dist: requests-oauthlib (==1.3.0)
Requires-Dist: rsa (==4.7.2)
Requires-Dist: scikit-image (==0.17.2)
Requires-Dist: scipy (==1.5.4)
Requires-Dist: six (==1.15.0)
Requires-Dist: tensorboard (==2.6.0)
Requires-Dist: tensorboard-data-server (==0.6.1)
Requires-Dist: tensorboard-plugin-wit (==1.8.0)
Requires-Dist: tensorflow (==2.4.0)
Requires-Dist: tensorflow-estimator (==2.4.0)
Requires-Dist: termcolor (==1.1.0)
Requires-Dist: tifffile (==2020.9.3)
Requires-Dist: tqdm (==4.62.2)
Requires-Dist: typing-extensions (==3.7.4.3)
Requires-Dist: urllib3 (==1.26.6)
Requires-Dist: Werkzeug (==2.0.1)
Requires-Dist: wrapt (==1.12.1)
Requires-Dist: zipp (==3.5.0)
